{"files":{"libs/docs/dist/index.d.mts":{"size":631,"mtime_nanos":1784154527886841000,"mode":420,"is_dir":false},"libs/docs/dist/index.mjs":{"size":51051,"mtime_nanos":1784154522023671800,"mode":420,"is_dir":false},"libs/docs/.turbo/turbo-build.log":{"size":911,"mtime_nanos":1784154528037353500,"mode":420,"is_dir":false},"libs/docs/dist":{"size":0,"mtime_nanos":0,"mode":0,"is_dir":true},"libs/docs/dist/index.js.map":{"size":83230,"mtime_nanos":1784154522029389200,"mode":420,"is_dir":false},"libs/docs/dist/index.d.ts":{"size":631,"mtime_nanos":1784154527890527600,"mode":420,"is_dir":false},"libs/docs/dist/index.mjs.map":{"size":83443,"mtime_nanos":1784154522028753700,"mode":420,"is_dir":false},"libs/docs/dist/index.js":{"size":53085,"mtime_nanos":1784154522024262900,"mode":420,"is_dir":false}},"order":["libs/docs/.turbo/turbo-build.log","libs/docs/dist","libs/docs/dist/index.d.mts","libs/docs/dist/index.d.ts","libs/docs/dist/index.js","libs/docs/dist/index.js.map","libs/docs/dist/index.mjs","libs/docs/dist/index.mjs.map"]}